[{"event": 2, "level": 14, "heal": 0.952681573731035, "damage": 0.35400000000000026, "op_lvl": 0.4, "badge": 0, "explore": 2.64}, {"event": 3, "level": 14, "heal": 3.563903559720462, "damage": 0.18800000000000014, "op_lvl": 0.4, "badge": 2, "explore": 5.132}, {"event": 2, "level": 10, "heal": 4.54767632996166, "damage": 0.17500000000000013, "op_lvl": 0.4, "badge": 0, "explore": 4.66}, {"event": 2, "level": 10, "heal": 2.190285840949457, "damage": 0.1500000000000001, "op_lvl": 0.4, "badge": 0, "explore": 4.0440000000000005}, {"event": 0, "level": 8, "heal": 3.210891145467804, "damage": 0.17600000000000013, "op_lvl": 0.2, "badge": 0, "explore": 3.544}, {"event": 1, "level": 6, "heal": 3.781543946249829, "damage": 0.1570000000000001, "op_lvl": 0.4, "badge": 0, "explore": 4.492}, {"event": 0, "level": 6, "heal": 2.6609508138919904, "damage": 0.2710000000000002, "op_lvl": 0.4, "badge": 0, "explore": 3.688}, {"event": 3, "level": 14, "heal": 4.173415855625324, "damage": 0.18800000000000014, "op_lvl": 0.4, "badge": 0, "explore": 4.832}, {"event": 2, "level": 18, "heal": 3.1228635539727767, "damage": 0.16100000000000012, "op_lvl": 0.4, "badge": 0, "explore": 4.768}, {"event": 2, "level": 16, "heal": 3.9665936832743474, "damage": 0.1410000000000001, "op_lvl": 0.4, "badge": 0, "explore": 4.744}, {"event": 2, "level": 18, "heal": 2.5184280217273964, "damage": 0.18400000000000014, "op_lvl": 0.4, "badge": 0, "explore": 4.604}, {"event": 0, "level": 9, "heal": 1.003395749370982, "damage": 0.10500000000000008, "op_lvl": 0.0, "badge": 0, "explore": 3.2560000000000002}, {"event": 0, "level": 11, "heal": 0.7950236325819684, "damage": 0.10900000000000008, "op_lvl": 0.4, "badge": 0, "explore": 4.228}, {"event": 0, "level": 10, "heal": 1.4590959868514992, "damage": 0.18900000000000014, "op_lvl": 0.0, "badge": 0, "explore": 3.156}, {"event": 0, "level": 11, "heal": 1.1871088248317816, "damage": 0.1560000000000001, "op_lvl": 0.0, "badge": 0, "explore": 3.172}, {"event": 2, "level": 12, "heal": 6.431101463051313, "damage": 0.20100000000000015, "op_lvl": 0.4, "badge": 0, "explore": 5.216}, {"event": 2, "level": 17, "heal": 4.670148183835739, "damage": 0.17800000000000013, "op_lvl": 0.4, "badge": 0, "explore": 4.716}, {"event": 0, "level": 11, "heal": 5.656562703416952, "damage": 0.7320000000000005, "op_lvl": 0.2, "badge": 0, "explore": 3.512}, {"event": 0, "level": 13, "heal": 0.8124585300981806, "damage": 0.17500000000000013, "op_lvl": 0.4, "badge": 0, "explore": 3.3160000000000003}, {"event": 2, "level": 13, "heal": 3.7919585281427457, "damage": 0.17700000000000013, "op_lvl": 0.4, "badge": 0, "explore": 5.144}, {"event": 0, "level": 9, "heal": 1.144504559767717, "damage": 0.20400000000000015, "op_lvl": 0.4, "badge": 0, "explore": 3.46}, {"event": 3, "level": 13, "heal": 3.4659130132365723, "damage": 0.17800000000000013, "op_lvl": 0.4, "badge": 0, "explore": 4.876}, {"event": 1, "level": 13, "heal": 1.14533659995431, "damage": 0.16100000000000012, "op_lvl": 0.4, "badge": 0, "explore": 4.724}, {"event": 0, "level": 9, "heal": 0.40118523976574527, "damage": 0.1310000000000001, "op_lvl": 0.2, "badge": 0, "explore": 3.644}, {"event": 0, "level": 12, "heal": 3.87140220535401, "damage": 0.2470000000000002, "op_lvl": 0.2, "badge": 0, "explore": 3.564}, {"event": 2, "level": 12, "heal": 8.733794884510456, "damage": 0.19000000000000014, "op_lvl": 0.4, "badge": 0, "explore": 5.232}, {"event": 2, "level": 12, "heal": 5.6672416024308365, "damage": 0.20700000000000016, "op_lvl": 0.4, "badge": 0, "explore": 4.644}, {"event": 1, "level": 11, "heal": 5.79658521348822, "damage": 0.8850000000000007, "op_lvl": 0.4, "badge": 0, "explore": 4.184}, {"event": 0, "level": 10, "heal": 1.3452741336010332, "damage": 0.17800000000000013, "op_lvl": 0.4, "badge": 0, "explore": 3.42}, {"event": 3, "level": 12, "heal": 5.681051274408272, "damage": 0.20100000000000015, "op_lvl": 0.4, "badge": 2, "explore": 4.744}, {"event": 1, "level": 12, "heal": 4.296567778025376, "damage": 0.21800000000000017, "op_lvl": 0.4, "badge": 0, "explore": 4.0120000000000005}, {"event": 4, "level": 13, "heal": 5.775538255598789, "damage": 0.44700000000000034, "op_lvl": 0.4, "badge": 2, "explore": 4.28}, {"event": 0, "level": 12, "heal": 3.378706977370525, "damage": 0.21600000000000016, "op_lvl": 0.2, "badge": 0, "explore": 2.8040000000000003}, {"event": 0, "level": 10, "heal": 0.6352652023344266, "damage": 0.2680000000000002, "op_lvl": 0.4, "badge": 0, "explore": 3.208}, {"event": 2, "level": 18, "heal": 4.022056958269731, "damage": 0.21000000000000016, "op_lvl": 0.4, "badge": 0, "explore": 4.744}, {"event": 0, "level": 7, "heal": 2.094903900799144, "damage": 0.25300000000000017, "op_lvl": 0.0, "badge": 0, "explore": 3.068}, {"event": 0, "level": 6, "heal": 2.1290924761513, "damage": 0.6890000000000005, "op_lvl": 0.2, "badge": 0, "explore": 3.728}, {"event": 0, "level": 12, "heal": 5.1368444804715665, "damage": 0.5150000000000003, "op_lvl": 0.4, "badge": 0, "explore": 3.54}, {"event": 0, "level": 10, "heal": 0.5818164551356662, "damage": 0.20600000000000016, "op_lvl": 0.4, "badge": 0, "explore": 4.54}, {"event": 0, "level": 5, "heal": 0.8406410958135093, "damage": 0.047000000000000035, "op_lvl": 0.0, "badge": 0, "explore": 2.2560000000000002}, {"event": 3, "level": 12, "heal": 5.496455535758193, "damage": 0.2440000000000002, "op_lvl": 0.4, "badge": 2, "explore": 4.664}, {"event": 0, "level": 6, "heal": 2.5047614150555333, "damage": 0.2450000000000002, "op_lvl": 0.2, "badge": 0, "explore": 2.964}, {"event": 0, "level": 10, "heal": 2.8147771603447236, "damage": 0.20600000000000016, "op_lvl": 0.4, "badge": 0, "explore": 4.056}, {"event": 2, "level": 12, "heal": 5.984078887874359, "damage": 0.20400000000000015, "op_lvl": 0.4, "badge": 0, "explore": 4.868}, {"event": 2, "level": 17, "heal": 4.040822320958166, "damage": 0.16400000000000012, "op_lvl": 0.4, "badge": 0, "explore": 4.616}, {"event": 0, "level": 9, "heal": 1.3156593260367222, "damage": 0.18300000000000013, "op_lvl": 0.0, "badge": 0, "explore": 3.568}, {"event": 2, "level": 10, "heal": 4.948998825170124, "damage": 0.1210000000000001, "op_lvl": 0.4, "badge": 0, "explore": 4.936}, {"event": 1, "level": 14, "heal": 5.681420916298559, "damage": 0.16500000000000012, "op_lvl": 0.4, "badge": 0, "explore": 5.24}, {"event": 3, "level": 10, "heal": 7.9796829317432385, "damage": 0.47600000000000037, "op_lvl": 0.4, "badge": 2, "explore": 5.0360000000000005}, {"event": 2, "level": 13, "heal": 4.602744768840998, "damage": 0.19600000000000015, "op_lvl": 0.4, "badge": 0, "explore": 4.956}, {"event": 0, "level": 10, "heal": 2.815939730441747, "damage": 0.2420000000000002, "op_lvl": 0.4, "badge": 0, "explore": 2.98}, {"event": 1, "level": 6, "heal": 2.844374742904155, "damage": 0.19300000000000014, "op_lvl": 0.4, "badge": 0, "explore": 4.016}, {"event": 0, "level": 6, "heal": 0.37878292843810113, "damage": 0.10100000000000008, "op_lvl": 0.2, "badge": 0, "explore": 3.528}, {"event": 0, "level": 10, "heal": 3.291291829287587, "damage": 0.1410000000000001, "op_lvl": 0.4, "badge": 0, "explore": 4.448}, {"event": 0, "level": 10, "heal": 3.8829349987144264, "damage": 0.18400000000000014, "op_lvl": 0.4, "badge": 0, "explore": 3.14}, {"event": 0, "level": 13, "heal": 3.556313721379465, "damage": 0.19300000000000014, "op_lvl": 0.2, "badge": 0, "explore": 3.684}, {"event": 0, "level": 8, "heal": 3.7142929867067793, "damage": 0.1520000000000001, "op_lvl": 0.0, "badge": 0, "explore": 3.2}, {"event": 0, "level": 18, "heal": 0.7446351538579532, "damage": 0.19800000000000015, "op_lvl": 0.4, "badge": 0, "explore": 4.176}, {"event": 0, "level": 11, "heal": 1.3566116018491365, "damage": 0.21700000000000016, "op_lvl": 0.2, "badge": 0, "explore": 2.992}, {"event": 0, "level": 10, "heal": 3.3924267359612195, "damage": 0.20300000000000015, "op_lvl": 0.0, "badge": 0, "explore": 3.212}, {"event": 0, "level": 10, "heal": 4.183669674775681, "damage": 0.3020000000000002, "op_lvl": 0.0, "badge": 0, "explore": 2.392}, {"event": 3, "level": 13, "heal": 6.048796220511376, "damage": 0.21800000000000017, "op_lvl": 0.4, "badge": 2, "explore": 5.112}, {"event": 0, "level": 4, "heal": 1.1476043183360252, "damage": 0.06300000000000004, "op_lvl": 0.2, "badge": 0, "explore": 2.832}, {"event": 0, "level": 6, "heal": 1.0282967032967036, "damage": 0.22000000000000017, "op_lvl": 0.2, "badge": 0, "explore": 3.448}, {"event": 0, "level": 8, "heal": 0.40725535020201004, "damage": 0.1310000000000001, "op_lvl": 0.0, "badge": 0, "explore": 3.3240000000000003}, {"event": 3, "level": 13, "heal": 7.690902013392437, "damage": 0.21300000000000016, "op_lvl": 0.4, "badge": 2, "explore": 4.636}, {"event": 0, "level": 10, "heal": 2.1369209456436886, "damage": 0.19400000000000014, "op_lvl": 0.4, "badge": 0, "explore": 3.932}, {"event": 0, "level": 10, "heal": 1.2389301544937932, "damage": 0.23500000000000018, "op_lvl": 0.4, "badge": 0, "explore": 3.364}, {"event": 2, "level": 14, "heal": 5.4726547517816835, "damage": 0.16000000000000011, "op_lvl": 0.4, "badge": 0, "explore": 4.0600000000000005}, {"event": 0, "level": 10, "heal": 1.4451533009260926, "damage": 0.17800000000000013, "op_lvl": 0.4, "badge": 0, "explore": 4.412}, {"event": 0, "level": 10, "heal": 2.249195593406201, "damage": 0.19800000000000015, "op_lvl": 0.0, "badge": 0, "explore": 3.536}, {"event": 2, "level": 11, "heal": 4.263793155072119, "damage": 0.17200000000000013, "op_lvl": 0.4, "badge": 0, "explore": 4.764}, {"event": 0, "level": 10, "heal": 2.4545207616299307, "damage": 0.20800000000000016, "op_lvl": 0.4, "badge": 0, "explore": 4.412}, {"event": 0, "level": 11, "heal": 4.149809343566858, "damage": 0.18500000000000014, "op_lvl": 0.4, "badge": 0, "explore": 3.8280000000000003}, {"event": 2, "level": 13, "heal": 5.8440988014153445, "damage": 0.1320000000000001, "op_lvl": 0.4, "badge": 0, "explore": 4.3}, {"event": 3, "level": 12, "heal": 8.01382016876357, "damage": 0.2440000000000002, "op_lvl": 0.4, "badge": 2, "explore": 4.808}, {"event": 0, "level": 10, "heal": 2.6282704719065606, "damage": 0.19700000000000015, "op_lvl": 0.4, "badge": 0, "explore": 4.18}, {"event": 2, "level": 14, "heal": 2.5594981435728985, "damage": 0.18900000000000014, "op_lvl": 0.4, "badge": 0, "explore": 4.88}, {"event": 0, "level": 9, "heal": 3.115351342654905, "damage": 0.21800000000000017, "op_lvl": 0.0, "badge": 0, "explore": 3.3240000000000003}, {"event": 1, "level": 11, "heal": 3.6397085451907527, "damage": 0.16500000000000012, "op_lvl": 0.4, "badge": 0, "explore": 4.224}, {"event": 0, "level": 12, "heal": 4.188868988767839, "damage": 0.18500000000000014, "op_lvl": 0.0, "badge": 0, "explore": 2.164}, {"event": 0, "level": 14, "heal": 0.4931172810418092, "damage": 0.2460000000000002, "op_lvl": 0.0, "badge": 0, "explore": 2.056}, {"event": 0, "level": 12, "heal": 2.514184836412148, "damage": 0.20000000000000015, "op_lvl": 0.4, "badge": 0, "explore": 3.548}, {"event": 0, "level": 16, "heal": 1.4029656916117452, "damage": 0.20200000000000015, "op_lvl": 0.4, "badge": 0, "explore": 3.644}, {"event": 2, "level": 12, "heal": 4.477787010395009, "damage": 0.2440000000000002, "op_lvl": 0.4, "badge": 0, "explore": 4.856}, {"event": 0, "level": 11, "heal": 1.4056273826677899, "damage": 0.35900000000000026, "op_lvl": 0.2, "badge": 0, "explore": 3.2720000000000002}, {"event": 2, "level": 8, "heal": 3.7193070050967716, "damage": 0.22200000000000017, "op_lvl": 0.4, "badge": 0, "explore": 4.892}, {"event": 0, "level": 9, "heal": 2.2317760125206636, "damage": 0.1420000000000001, "op_lvl": 0.2, "badge": 0, "explore": 3.976}, {"event": 1, "level": 14, "heal": 2.1432277947883525, "damage": 0.18100000000000013, "op_lvl": 0.4, "badge": 0, "explore": 4.712}, {"event": 0, "level": 10, "heal": 2.293947625078621, "damage": 0.17900000000000013, "op_lvl": 0.2, "badge": 0, "explore": 3.68}, {"event": 2, "level": 12, "heal": 6.430839417299863, "damage": 0.21300000000000016, "op_lvl": 0.4, "badge": 0, "explore": 4.868}, {"event": 0, "level": 9, "heal": 2.604552381881185, "damage": 0.17100000000000012, "op_lvl": 0.2, "badge": 0, "explore": 4.276}, {"event": 0, "level": 10, "heal": 2.5236392256978974, "damage": 0.21400000000000016, "op_lvl": 0.4, "badge": 0, "explore": 3.604}, {"event": 2, "level": 9, "heal": 3.1859485032859647, "damage": 0.16100000000000012, "op_lvl": 0.4, "badge": 0, "explore": 5.7}, {"event": 0, "level": 14, "heal": 1.419901874239245, "damage": 0.33500000000000024, "op_lvl": 0.0, "badge": 0, "explore": 2.536}, {"event": 0, "level": 8, "heal": 2.3120807219249935, "damage": 0.1520000000000001, "op_lvl": 0.0, "badge": 0, "explore": 3.376}, {"event": 0, "level": 9, "heal": 2.2265644162473968, "damage": 0.17400000000000013, "op_lvl": 0.0, "badge": 0, "explore": 3.96}, {"event": 0, "level": 15, "heal": 1.40372991007348, "damage": 0.17700000000000013, "op_lvl": 0.4, "badge": 0, "explore": 3.364}, {"event": 3, "level": 11, "heal": 5.430369652619969, "damage": 0.2750000000000002, "op_lvl": 0.4, "badge": 2, "explore": 5.5040000000000004}, {"event": 0, "level": 11, "heal": 2.7041286790046337, "damage": 0.1490000000000001, "op_lvl": 0.0, "badge": 0, "explore": 3.88}, {"event": 0, "level": 11, "heal": 2.149792763110294, "damage": 0.1500000000000001, "op_lvl": 0.2, "badge": 0, "explore": 3.7640000000000002}, {"event": 0, "level": 9, "heal": 2.101697525835457, "damage": 0.1590000000000001, "op_lvl": 0.2, "badge": 0, "explore": 4.14}, {"event": 0, "level": 8, "heal": 0.46390467769778126, "damage": 0.10200000000000008, "op_lvl": 0.0, "badge": 0, "explore": 4.096}, {"event": 0, "level": 6, "heal": 1.5300180024317962, "damage": 0.09600000000000007, "op_lvl": 0.0, "badge": 0, "explore": 3.968}, {"event": 0, "level": 9, "heal": 2.9562782381547823, "damage": 0.19300000000000014, "op_lvl": 0.2, "badge": 0, "explore": 3.868}, {"event": 0, "level": 10, "heal": 2.27384177695116, "damage": 0.19400000000000014, "op_lvl": 0.0, "badge": 0, "explore": 3.384}, {"event": 0, "level": 7, "heal": 3.527642462802798, "damage": 0.11900000000000009, "op_lvl": 0.0, "badge": 0, "explore": 3.7520000000000002}, {"event": 0, "level": 11, "heal": 2.325708497775955, "damage": 0.17500000000000013, "op_lvl": 0.0, "badge": 0, "explore": 2.7520000000000002}, {"event": 0, "level": 12, "heal": 1.2340915546354556, "damage": 0.1460000000000001, "op_lvl": 0.0, "badge": 0, "explore": 3.8200000000000003}, {"event": 0, "level": 10, "heal": 1.0963782594550189, "damage": 0.1500000000000001, "op_lvl": 0.0, "badge": 0, "explore": 3.404}, {"event": 0, "level": 9, "heal": 2.986430022358832, "damage": 0.17900000000000013, "op_lvl": 0.0, "badge": 0, "explore": 3.1}, {"event": 0, "level": 8, "heal": 2.8485345011207084, "damage": 0.11400000000000009, "op_lvl": 0.0, "badge": 0, "explore": 4.112}, {"event": 0, "level": 10, "heal": 2.4057800099128697, "damage": 0.17300000000000013, "op_lvl": 0.2, "badge": 0, "explore": 3.888}, {"event": 0, "level": 12, "heal": 4.032887409580653, "damage": 0.18600000000000014, "op_lvl": 0.4, "badge": 0, "explore": 3.72}, {"event": 0, "level": 10, "heal": 5.668474296491123, "damage": 0.18500000000000014, "op_lvl": 0.0, "badge": 0, "explore": 2.924}, {"event": 0, "level": 10, "heal": 2.951003516904639, "damage": 0.2440000000000002, "op_lvl": 0.2, "badge": 0, "explore": 2.948}, {"event": 0, "level": 12, "heal": 2.3869418265549944, "damage": 0.18800000000000014, "op_lvl": 0.0, "badge": 0, "explore": 3.164}, {"event": 0, "level": 10, "heal": 4.246113804930792, "damage": 0.19700000000000015, "op_lvl": 0.2, "badge": 0, "explore": 3.468}, {"event": 0, "level": 8, "heal": 3.3199618343432236, "damage": 0.12500000000000008, "op_lvl": 0.0, "badge": 0, "explore": 3.552}, {"event": 0, "level": 10, "heal": 4.027231432519989, "damage": 0.20200000000000015, "op_lvl": 0.0, "badge": 0, "explore": 3.332}, {"event": 0, "level": 10, "heal": 1.6766553346239654, "damage": 0.2440000000000002, "op_lvl": 0.0, "badge": 0, "explore": 3.092}, {"event": 0, "level": 9, "heal": 2.2211021042564285, "damage": 0.11100000000000008, "op_lvl": 0.4, "badge": 0, "explore": 3.2520000000000002}, {"event": 0, "level": 10, "heal": 3.566703569929376, "damage": 0.20700000000000016, "op_lvl": 0.0, "badge": 0, "explore": 3.3080000000000003}, {"event": 0, "level": 11, "heal": 2.6986620130372856, "damage": 0.25500000000000017, "op_lvl": 0.2, "badge": 0, "explore": 2.952}, {"event": 0, "level": 9, "heal": 4.801693706476799, "damage": 0.19300000000000014, "op_lvl": 0.0, "badge": 0, "explore": 3.06}, {"event": 0, "level": 9, "heal": 3.7736903070424828, "damage": 0.1440000000000001, "op_lvl": 0.0, "badge": 0, "explore": 3.904}, {"event": 0, "level": 10, "heal": 2.1390836317475026, "damage": 0.1530000000000001, "op_lvl": 0.0, "badge": 0, "explore": 3.556}, {"event": 0, "level": 9, "heal": 2.1519716728559883, "damage": 0.21100000000000016, "op_lvl": 0.4, "badge": 0, "explore": 3.616}, {"event": 0, "level": 5, "heal": 0.5763959842235511, "damage": 0.09600000000000007, "op_lvl": 0.0, "badge": 0, "explore": 3.852}, {"event": 0, "level": 10, "heal": 3.8009106113944826, "damage": 0.2700000000000002, "op_lvl": 0.4, "badge": 0, "explore": 3.584}, {"event": 0, "level": 9, "heal": 2.318769377376163, "damage": 0.1550000000000001, "op_lvl": 0.2, "badge": 0, "explore": 3.7}, {"event": 2, "level": 11, "heal": 9.33283598099667, "damage": 0.19300000000000014, "op_lvl": 0.4, "badge": 0, "explore": 4.5040000000000004}, {"event": 0, "level": 10, "heal": 4.061824011163451, "damage": 0.1590000000000001, "op_lvl": 0.2, "badge": 0, "explore": 3.196}, {"event": 0, "level": 9, "heal": 4.785785374423023, "damage": 0.1570000000000001, "op_lvl": 0.0, "badge": 0, "explore": 2.94}, {"event": 0, "level": 9, "heal": 2.406099515721318, "damage": 0.16200000000000012, "op_lvl": 0.0, "badge": 0, "explore": 3.728}, {"event": 0, "level": 12, "heal": 4.564693539036316, "damage": 0.23400000000000018, "op_lvl": 0.0, "badge": 0, "explore": 2.02}, {"event": 0, "level": 7, "heal": 2.6678785989130813, "damage": 0.08300000000000006, "op_lvl": 0.2, "badge": 0, "explore": 3.34}, {"event": 0, "level": 11, "heal": 4.234049849054823, "damage": 0.1560000000000001, "op_lvl": 0.2, "badge": 0, "explore": 3.7600000000000002}, {"event": 0, "level": 8, "heal": 3.596248524933175, "damage": 0.1520000000000001, "op_lvl": 0.0, "badge": 0, "explore": 3.36}, {"event": 2, "level": 13, "heal": 2.4983032800483187, "damage": 0.25500000000000017, "op_lvl": 0.4, "badge": 0, "explore": 5.192}, {"event": 0, "level": 8, "heal": 4.03205137511311, "damage": 0.1400000000000001, "op_lvl": 0.0, "badge": 0, "explore": 3.432}, {"event": 0, "level": 9, "heal": 3.022759868597187, "damage": 0.2840000000000002, "op_lvl": 0.4, "badge": 0, "explore": 3.572}, {"event": 3, "level": 13, "heal": 6.6782095379949205, "damage": 0.23300000000000018, "op_lvl": 0.4, "badge": 0, "explore": 4.564}, {"event": 1, "level": 12, "heal": 3.957809166278544, "damage": 0.21700000000000016, "op_lvl": 0.4, "badge": 0, "explore": 3.8000000000000003}, {"event": 2, "level": 10, "heal": 8.053579653204237, "damage": 0.17900000000000013, "op_lvl": 0.4, "badge": 0, "explore": 5.308}, {"event": 0, "level": 6, "heal": 2.8710671084526096, "damage": 0.22500000000000017, "op_lvl": 0.2, "badge": 0, "explore": 3.74}, {"event": 3, "level": 13, "heal": 7.323481214639692, "damage": 0.21600000000000016, "op_lvl": 0.4, "badge": 2, "explore": 4.496}, {"event": 2, "level": 11, "heal": 5.090858941134085, "damage": 0.18700000000000014, "op_lvl": 0.4, "badge": 0, "explore": 5.128}, {"event": 0, "level": 9, "heal": 2.436046657640779, "damage": 0.1530000000000001, "op_lvl": 0.2, "badge": 0, "explore": 3.204}, {"event": 0, "level": 10, "heal": 2.3530068082053943, "damage": 0.17600000000000013, "op_lvl": 0.2, "badge": 0, "explore": 3.56}, {"event": 0, "level": 7, "heal": 2.2595714897160946, "damage": 0.11600000000000009, "op_lvl": 0.2, "badge": 0, "explore": 3.444}, {"event": 0, "level": 13, "heal": 1.1580947242559234, "damage": 0.20300000000000015, "op_lvl": 0.0, "badge": 0, "explore": 3.084}, {"event": 3, "level": 13, "heal": 4.239440152501423, "damage": 0.23600000000000018, "op_lvl": 0.4, "badge": 2, "explore": 4.5520000000000005}, {"event": 0, "level": 11, "heal": 2.3879815058018963, "damage": 0.17200000000000013, "op_lvl": 0.2, "badge": 0, "explore": 3.716}, {"event": 0, "level": 5, "heal": 1.9317201213752941, "damage": 0.06100000000000005, "op_lvl": 0.0, "badge": 0, "explore": 2.728}, {"event": 0, "level": 5, "heal": 3.9160483897326, "damage": 0.06400000000000004, "op_lvl": 0.0, "badge": 0, "explore": 1.6400000000000001}, {"event": 0, "level": 7, "heal": 1.4139329067749007, "damage": 0.1230000000000001, "op_lvl": 0.2, "badge": 0, "explore": 3.624}, {"event": 0, "level": 15, "heal": 1.216123481039812, "damage": 0.22700000000000017, "op_lvl": 0.4, "badge": 0, "explore": 3.476}, {"event": 0, "level": 10, "heal": 2.226566176492352, "damage": 0.16100000000000012, "op_lvl": 0.2, "badge": 0, "explore": 3.516}, {"event": 0, "level": 10, "heal": 1.2379589108863467, "damage": 0.19800000000000015, "op_lvl": 0.4, "badge": 0, "explore": 4.148}, {"event": 0, "level": 11, "heal": 3.755126037504647, "damage": 0.19500000000000015, "op_lvl": 0.0, "badge": 0, "explore": 3.492}, {"event": 0, "level": 14, "heal": 1.168442953441823, "damage": 0.23000000000000018, "op_lvl": 0.4, "badge": 0, "explore": 4.292}, {"event": 2, "level": 14, "heal": 7.042311988666171, "damage": 0.21700000000000016, "op_lvl": 0.4, "badge": 0, "explore": 4.16}, {"event": 3, "level": 11, "heal": 6.727720614570739, "damage": 0.16800000000000012, "op_lvl": 0.4, "badge": 0, "explore": 5.024}, {"event": 0, "level": 12, "heal": 2.4153876591911505, "damage": 0.21100000000000016, "op_lvl": 0.2, "badge": 0, "explore": 3.444}, {"event": 0, "level": 13, "heal": 0.5746361883088789, "damage": 0.3850000000000003, "op_lvl": 0.2, "badge": 0, "explore": 3.016}, {"event": 1, "level": 11, "heal": 2.6334222899910205, "damage": 0.2630000000000002, "op_lvl": 0.4, "badge": 0, "explore": 3.7640000000000002}, {"event": 0, "level": 9, "heal": 0.6797883367289516, "damage": 0.16500000000000012, "op_lvl": 0.0, "badge": 0, "explore": 3.436}, {"event": 2, "level": 12, "heal": 8.223341523037263, "damage": 0.22300000000000017, "op_lvl": 0.4, "badge": 0, "explore": 4.272}, {"event": 0, "level": 5, "heal": 1.4706562189399721, "damage": 0.12700000000000009, "op_lvl": 0.4, "badge": 0, "explore": 2.652}, {"event": 0, "level": 7, "heal": 0.8351202211046479, "damage": 0.12600000000000008, "op_lvl": 0.0, "badge": 0, "explore": 3.94}, {"event": 0, "level": 7, "heal": 2.1536192332632824, "damage": 0.09800000000000007, "op_lvl": 0.0, "badge": 0, "explore": 3.54}, {"event": 0, "level": 10, "heal": 3.7355943952311392, "damage": 0.1460000000000001, "op_lvl": 0.0, "badge": 0, "explore": 2.948}, {"event": 0, "level": 10, "heal": 4.6214626823784055, "damage": 0.16800000000000012, "op_lvl": 0.2, "badge": 0, "explore": 3.128}, {"event": 0, "level": 9, "heal": 2.453397376575909, "damage": 0.1580000000000001, "op_lvl": 0.0, "badge": 0, "explore": 3.66}, {"event": 0, "level": 9, "heal": 2.1464993514353914, "damage": 0.2600000000000002, "op_lvl": 0.2, "badge": 0, "explore": 3.5}, {"event": 0, "level": 13, "heal": 4.032823103681956, "damage": 0.19100000000000014, "op_lvl": 0.4, "badge": 0, "explore": 3.7720000000000002}, {"event": 0, "level": 12, "heal": 2.6369020631984394, "damage": 0.2590000000000002, "op_lvl": 0.4, "badge": 0, "explore": 3.8320000000000003}, {"event": 0, "level": 11, "heal": 4.145865001115473, "damage": 0.22100000000000017, "op_lvl": 0.2, "badge": 0, "explore": 3.44}, {"event": 0, "level": 11, "heal": 3.3736274880120725, "damage": 0.20700000000000016, "op_lvl": 0.2, "badge": 0, "explore": 3.544}, {"event": 0, "level": 11, "heal": 1.8876054996499283, "damage": 0.2820000000000002, "op_lvl": 0.4, "badge": 0, "explore": 3.72}, {"event": 3, "level": 12, "heal": 4.426682961793775, "damage": 0.22200000000000017, "op_lvl": 0.4, "badge": 2, "explore": 4.572}, {"event": 0, "level": 10, "heal": 4.539929189946367, "damage": 0.19900000000000015, "op_lvl": 0.2, "badge": 0, "explore": 3.552}, {"event": 0, "level": 12, "heal": 1.266352784915894, "damage": 0.20200000000000015, "op_lvl": 0.4, "badge": 0, "explore": 4.124}, {"event": 0, "level": 6, "heal": 4.95905796152506, "damage": 0.20000000000000015, "op_lvl": 0.4, "badge": 0, "explore": 3.928}, {"event": 0, "level": 14, "heal": 2.631719556618775, "damage": 0.21300000000000016, "op_lvl": 0.0, "badge": 0, "explore": 2.052}, {"event": 0, "level": 10, "heal": 4.098130144697848, "damage": 0.18600000000000014, "op_lvl": 0.0, "badge": 0, "explore": 3.164}, {"event": 0, "level": 11, "heal": 1.0616709871267964, "damage": 0.16700000000000012, "op_lvl": 0.4, "badge": 0, "explore": 4.184}, {"event": 0, "level": 14, "heal": 1.6829663009665359, "damage": 0.33400000000000024, "op_lvl": 0.4, "badge": 0, "explore": 3.108}, {"event": 0, "level": 8, "heal": 4.415236084257218, "damage": 0.1470000000000001, "op_lvl": 0.2, "badge": 0, "explore": 3.2560000000000002}, {"event": 2, "level": 13, "heal": 6.380222965187469, "damage": 0.19800000000000015, "op_lvl": 0.4, "badge": 0, "explore": 4.992}, {"event": 1, "level": 13, "heal": 4.330408917481135, "damage": 0.19900000000000015, "op_lvl": 0.4, "badge": 0, "explore": 3.8280000000000003}, {"event": 0, "level": 11, "heal": 2.2299528609276367, "damage": 0.20100000000000015, "op_lvl": 0.4, "badge": 0, "explore": 4.292}, {"event": 0, "level": 11, "heal": 3.837496557703017, "damage": 0.43200000000000033, "op_lvl": 0.2, "badge": 0, "explore": 4.0840000000000005}, {"event": 1, "level": 11, "heal": 2.4572900289832496, "damage": 0.17600000000000013, "op_lvl": 0.4, "badge": 0, "explore": 4.284}, {"event": 2, "level": 10, "heal": 7.028091964729897, "damage": 0.16700000000000012, "op_lvl": 0.4, "badge": 0, "explore": 4.796}, {"event": 0, "level": 12, "heal": 2.443815619971569, "damage": 0.19100000000000014, "op_lvl": 0.4, "badge": 0, "explore": 4.048}, {"event": 0, "level": 7, "heal": 0.8304766798997651, "damage": 0.07800000000000006, "op_lvl": 0.2, "badge": 0, "explore": 2.62}, {"event": 0, "level": 9, "heal": 3.743806052273795, "damage": 0.18500000000000014, "op_lvl": 0.2, "badge": 0, "explore": 4.064}, {"event": 0, "level": 8, "heal": 4.560358672191264, "damage": 0.1230000000000001, "op_lvl": 0.0, "badge": 0, "explore": 3.8200000000000003}, {"event": 0, "level": 10, "heal": 2.9868628647421005, "damage": 0.17300000000000013, "op_lvl": 0.2, "badge": 0, "explore": 3.7600000000000002}, {"event": 0, "level": 6, "heal": 1.959029848685021, "damage": 0.1350000000000001, "op_lvl": 0.2, "badge": 0, "explore": 4.024}, {"event": 0, "level": 13, "heal": 1.1201081810512785, "damage": 0.20000000000000015, "op_lvl": 0.4, "badge": 0, "explore": 4.212}, {"event": 0, "level": 7, "heal": 3.401347161413902, "damage": 0.09500000000000007, "op_lvl": 0.0, "badge": 0, "explore": 3.44}, {"event": 0, "level": 10, "heal": 2.2076506955473776, "damage": 0.20000000000000015, "op_lvl": 0.2, "badge": 0, "explore": 3.868}, {"event": 2, "level": 10, "heal": 6.220412590150109, "damage": 0.1320000000000001, "op_lvl": 0.4, "badge": 0, "explore": 4.352}, {"event": 0, "level": 11, "heal": 2.288598462964589, "damage": 0.19900000000000015, "op_lvl": 0.4, "badge": 0, "explore": 3.632}, {"event": 0, "level": 8, "heal": 2.3775531095052784, "damage": 0.10000000000000007, "op_lvl": 0.2, "badge": 0, "explore": 3.36}, {"event": 0, "level": 12, "heal": 2.318186068497093, "damage": 0.18300000000000013, "op_lvl": 0.4, "badge": 0, "explore": 3.8160000000000003}, {"event": 0, "level": 11, "heal": 2.2852766716127966, "damage": 0.22300000000000017, "op_lvl": 0.2, "badge": 0, "explore": 3.7880000000000003}, {"event": 1, "level": 16, "heal": 1.2232079268685807, "damage": 0.18600000000000014, "op_lvl": 0.4, "badge": 0, "explore": 3.744}, {"event": 0, "level": 11, "heal": 2.4811192591618565, "damage": 0.23200000000000018, "op_lvl": 0.0, "badge": 0, "explore": 2.028}, {"event": 0, "level": 10, "heal": 2.2487052055702135, "damage": 0.1590000000000001, "op_lvl": 0.2, "badge": 0, "explore": 3.572}, {"event": 0, "level": 12, "heal": 3.5560580138174527, "damage": 0.17500000000000013, "op_lvl": 0.4, "badge": 0, "explore": 3.952}, {"event": 0, "level": 10, "heal": 2.16176796272818, "damage": 0.1380000000000001, "op_lvl": 0.4, "badge": 0, "explore": 2.984}]